{
   "@type" : "Passive Optical Scanner",
   "acronym" : "VIIRS band M3",
   "agency" : {
      "@type" : "Agency",
      "agencyType" : "GOVERNMENT"
   },
   "bandwidth" : 1e-08,
   "bitsPerPixel" : 12,
   "dataRate" : 5.9000000000000004,
   "fieldOfView" : {
      "@type" : "FieldOfView",
      "alongTrackFieldOfView" : 0.82640000000000002,
      "crossTrackFieldOfView" : 122.38,
      "sensorGeometry" : "RECTANGULAR"
   },
   "mass" : 275,
   "mountType" : "BODY",
   "name" : "Visible/Infrared Imager Radiometer Suite,VIIRS",
   "numberOfDetectorsColsCrossTrack" : 2048,
   "numberOfDetectorsRowsAlongTrack" : 16,
   "operatingWavelength" : 4.8800000000000003e-07,
   "opticsSysEff" : 0.80000000000000004,
   "orientation" : {
      "@type" : "Orientation",
      "convention" : "SIDE_LOOK",
      "sideLookAngle" : 0
   },
   "power" : 240,
   "scanTechnique" : "MATRIX_IMAGER",
   "techReadinessLevel" : 9
}
